pyconfman2/Exceptions.py
pyconfman2/Schema.py
pyconfman2/__init__.py
pyconfman2-1.0.0.dist-info/METADATA
pyconfman2-1.0.0.dist-info/WHEEL
pyconfman2-1.0.0.dist-info/licenses/LICENSE
pyconfman2-1.0.0.dist-info/RECORD
