Metadata-Version: 2.3
Name: pyconfman2
Version: 1.0.0
Summary: A python package for managing YAML configuration
Project-URL: Homepage, https://github.com/PhillypHenning/python-config-parser
Project-URL: Issues, https://github.com/PhillypHenning/python-config-parser/issues
Author-email: Phillyp Henning <phillyp.henning@gmail.com>
License-File: LICENSE
Classifier: License :: OSI Approved :: MIT License
Classifier: Operating System :: OS Independent
Classifier: Programming Language :: Python :: 3
Requires-Python: >=3.8
Requires-Dist: pyyaml
